{
  "slug": "template-763",
  "title": "Triple-buffered didactic analyzer",
  "subtitle": "Defessus amet tergo delectatio.",
  "paragraph1": "Alias urbanus cupiditas vomer taedium capitulus vae virgo. Decet amor voluptatum custodia vulariter crux cimentarius vero. Tactus placeat eveniet cunabula umerus agnitio benevolentia sordeo.\nPax sol sortitus abduco. Aperiam attero virtus considero. Desolo odio necessitatibus.",
  "paragraph2": "Tersus deleo nulla aggredior capillus dedecor. Tamdiu aequitas capillus asperiores minima ventosus dedico. Caveo coniuratio taceo unus.\nVespillo fuga depono a error velociter sortitus. Aliquid decretum consectetur appello cumque verumtamen acervus. Deorsum succedo textor cunabula canonicus desipio.",
  "image": "/images/img-4.jpg",
  "ctaText": "e-enable",
  "testimonial": "Aliquam vitae tracto condico comis theatrum quos.",
  "name": "Guadalupe Dickinson"
}