{
  "slug": "template-630",
  "title": "Monitored needs-based capability",
  "subtitle": "Campana ut appono vado tempore odit tego.",
  "paragraph1": "Solitudo comes utilis vulgivagus balbus vivo caelestis. Cur alveus cunabula ambulo textilis adnuo sumo complectus demitto. Uterque demonstro vix dolorum aeger defungo ager altus cattus.\nVoluntarius delicate occaecati apostolus audeo via tabula. Dens depopulo clibanus suppono toties voco. Aeneus acquiro contra adsuesco ustulo victoria tolero inventore caecus.",
  "paragraph2": "Laborum tersus aestas. Solum tempora curis defluo vehemens aspicio. Victoria talus caput vulnus caritas.\nCilicium synagoga quibusdam inflammatio ratione cunctatio maiores usus. Taceo summisse coerceo deprimo. Ocer corporis auditor corrupti celebrer coadunatio suppellex.",
  "image": "/images/img-1.jpg",
  "ctaText": "disintermediate",
  "testimonial": "Bellum ea vesco venio nobis cavus tredecim cohibeo carpo turba.",
  "name": "Camille Cummerata"
}