{
  "slug": "template-501",
  "title": "Visionary homogeneous secured line",
  "subtitle": "Aduro uter inflammatio votum aut antiquus quas tego.",
  "paragraph1": "Eligendi benigne decretum ex bestia paulatim nesciunt brevis attollo patrocinor. Delego calamitas adeptio asporto. Facilis strues hic annus aperio qui.\nClementia currus desolo. Carbo contigo valde theca creta taceo cena crur tamisium volup. Auditor subseco iure.",
  "paragraph2": "Degero conatus coerceo. Sint theatrum voluptate delicate cruciamentum tum celo. Caries casso damnatio demitto strenuus adiuvo defessus adinventitias amet audacia.\nFugit cresco subvenio aro tactus. Bellum amplus sufficio victus curis sordeo absens temperantia. Surculus taceo arx suffragium.",
  "image": "/images/img-2.jpg",
  "ctaText": "iterate",
  "testimonial": "Auxilium crapula qui accendo in.",
  "name": "Mr. Mathew Lind"
}