{
  "slug": "template-916",
  "title": "Synchronised high-level application",
  "subtitle": "Tristis contra verecundia inflammatio appono.",
  "paragraph1": "Tergo incidunt clarus. Fugiat cibo summisse sollicito facere utrimque. Decens aeger vehemens taceo talis.\nOfficia sed officia caries. Timor alias vorax dignissimos turba tergiversatio colo. Tracto corrigo laudantium venio tergeo.",
  "paragraph2": "Voluptatum cupiditas conservo. Coniecto traho ipsum utique solvo tracto ipsa. Textus virgo alias utroque minima thorax aer.\nCasso cras argentum vestrum uterque. Cilicium tremo ter pariatur corrupti appono fuga aiunt adfectus. Recusandae denique tumultus theatrum aedificium stultus veritatis decet apud vitium.",
  "image": "/images/img-2.jpg",
  "ctaText": "benchmark",
  "testimonial": "Correptius ancilla veniam.",
  "name": "Dr. Lester Pacocha"
}