{
  "slug": "template-114",
  "title": "Team-oriented regional orchestration",
  "subtitle": "Curtus uberrime censura.",
  "paragraph1": "Aer demum ager succedo. Caveo cohibeo creta arguo aggredior. Bardus error comminor odit ipsa.\nVigilo cogito non. Calcar suspendo aranea est accommodo aetas vaco. Confugo ipsam angustus soluta spero consectetur umquam pecto.",
  "paragraph2": "Strenuus ut cupiditas. Celo tolero consuasor supellex aegrotatio terebro deinde utrimque beatae tenuis. Aegre modi viscus socius cervus aestivus tactus.\nCaelestis similique accusantium vilis defendo. Tremo degusto summa. Abstergo carpo defleo.",
  "image": "/images/img-5.jpg",
  "ctaText": "reinvent",
  "testimonial": "Assumenda eaque vester.",
  "name": "Dr. Louis Kshlerin"
}