{
  "slug": "template-320",
  "title": "Realigned upward-trending core",
  "subtitle": "Quisquam depulso cervus inventore alioqui caelestis ea administratio volutabrum calco.",
  "paragraph1": "Repellat sono impedit laudantium bellicus. Ceno auctus speculum uterque sum stella tempus. Cotidie deinde adipisci.\nVentus appono hic provident ultio tamquam deinde vos tondeo deleniti. Super cultellus totidem adinventitias. Solium solutio ducimus rem bene demoror sublime cupio triduana.",
  "paragraph2": "Decumbo animadverto advoco desidero vulpes viduo celer amplus aestus. Modi totam dignissimos xiphias. Audax timidus clibanus capio supellex debitis defleo defero optio deprimo.\nArcesso curtus ater cohaero desparatus caelestis spes consequuntur. Labore comes pax centum sollers. Pauci suscipit torqueo ater deprecator bellum.",
  "image": "/images/img-1.jpg",
  "ctaText": "integrate",
  "testimonial": "Brevis repellendus sufficio beneficium speculum sed ipsa.",
  "name": "Ralph Pfannerstill Jr."
}