{
  "slug": "template-995",
  "title": "Synchronised logistical ability",
  "subtitle": "Tribuo tot tantillus.",
  "paragraph1": "Summa desipio nam civis totam demitto angelus vacuus. Tergum audeo somnus utrimque bestia complectus defleo. Denuncio alienus tam curriculum nesciunt.\nVerumtamen auctus cur vergo. Vomica cresco calco spargo taceo spes aperiam saepe vehemens substantia. Sum blanditiis caterva complectus curis abeo confugo creta.",
  "paragraph2": "Conicio iure denego deputo. Absorbeo inflammatio utilis voluptates statim dedecor auditor tres. Inflammatio demitto consequatur eum aeger.\nCorreptius quisquam venio adeptio attero enim aestus. Articulus canis cavus vallum dignissimos venustas peior uberrime venia. Reprehenderit undique amiculum decimus basium urbanus agnitio surgo.",
  "image": "/images/img-1.jpg",
  "ctaText": "envisioneer",
  "testimonial": "Voluptatum coerceo adulescens iste sophismata.",
  "name": "Miss Marcia Boehm"
}