{
  "slug": "template-844",
  "title": "Vision-oriented interactive throughput",
  "subtitle": "Architecto coruscus aestas.",
  "paragraph1": "Iste tandem vulgus volutabrum assentator texo beneficium dedico neque summa. Cumque sumptus tunc coniuratio subiungo comprehendo contigo. Color taceo terror deleniti solus altus.\nCarus damnatio vesco adeo. Coaegresco alienus agnosco cibo veritatis valetudo beneficium. Voluptatem celebrer defessus amo pectus ascisco audentia delicate arcus.",
  "paragraph2": "Odio sto conturbo. Deputo eaque peccatus cupio. Super terra xiphias coepi amitto.\nSuggero adhaero sufficio vulticulus corpus demoror trepide corona adamo degenero. Cupiditas provident cernuus strenuus defetiscor urbs sol. Arceo defleo adipisci curia cerno ara tabgo verumtamen paens.",
  "image": "/images/img-5.jpg",
  "ctaText": "envisioneer",
  "testimonial": "Desparatus tergeo vesper volva suus vicinus abbas virtus timidus.",
  "name": "Helen Ebert"
}