{
  "slug": "template-222",
  "title": "Down-sized cohesive capability",
  "subtitle": "Alias decerno amissio adinventitias tandem cetera verumtamen facere quo hic.",
  "paragraph1": "Adhuc terminatio vesper denuo vapulus vesper admiratio amita patrocinor delinquo. Quibusdam vilitas adsum minima commodo. Coma ambulo tabgo aliquid abduco celebrer laborum.\nInflammatio supra thesis arguo adficio aestas tredecim. Deleo templum confugo somnus callide. Vitiosus articulus animus aiunt videlicet.",
  "paragraph2": "Alveus tergo facere vis caveo vito tener. Aspicio antiquus aduro acceptus amiculum tergum confido amitto stabilis placeat. Verbum curto cariosus vacuus aegrotatio denuncio stipes aduro.\nTamdiu unde claudeo labore bestia commodi amplus alias. Suppono sumptus cohibeo desolo. Video caries claustrum.",
  "image": "/images/img-3.jpg",
  "ctaText": "empower",
  "testimonial": "Beatus coaegresco rem textilis.",
  "name": "Lorena Fay"
}