{
  "slug": "template-484",
  "title": "Front-line actuating flexibility",
  "subtitle": "Contigo turpis harum cinis curso.",
  "paragraph1": "Bestia veniam vobis canis. Umquam audio sui. Venia rerum validus sortitus antea tunc vitiosus sonitus.\nVicinus tricesimus animadverto approbo corporis valde atavus veritatis. Comburo cui bonus. Victus alienus tremo.",
  "paragraph2": "Adipiscor atrocitas cupiditas consuasor astrum. Pariatur benevolentia ascit tantum. Audentia quis adhuc sequi torrens adstringo eveniet contigo sopor.\nCaritas hic cibo vinitor curo. Modi quibusdam alter aegre corrigo tumultus. Colo conscendo ademptio cognomen stultus theca caritas spiritus.",
  "image": "/images/img-5.jpg",
  "ctaText": "iterate",
  "testimonial": "Uberrime crinis contabesco delicate balbus temeritas rerum deficio.",
  "name": "Carol Boyer-Turcotte"
}