{
  "slug": "template-582",
  "title": "Stand-alone zero tolerance internet solution",
  "subtitle": "Sub administratio amita consuasor spiritus.",
  "paragraph1": "Esse confero trucido blandior viduo aspernatur summisse bellicus illum apostolus. Neque decretum video et vita corrumpo ager vergo. Depromo vinitor thema aegrus conculco speciosus tripudio.\nCui suggero arto tergo thymbra denuo stipes alias. Appello ambulo contra. Altus conatus vos occaecati vetus sum aestivus adamo abbas.",
  "paragraph2": "Amet alienus vorax acerbitas aeternus adflicto approbo at caecus adeptio. Vitium clementia paens altus soluta careo. Tutamen verumtamen communis coruscus deduco derelinquo aut.\nAsperiores calculus suppono conatus teneo. Delicate est concedo iste defero auxilium arcus adimpleo. Suffragium vicissitudo supellex nemo vitium summopere attero cariosus officia.",
  "image": "/images/img-3.jpg",
  "ctaText": "harness",
  "testimonial": "Vitiosus placeat ulciscor cursim adflicto cruciamentum combibo currus totam stipes.",
  "name": "Lillie Hettinger"
}