{
  "slug": "template-993",
  "title": "User-centric multimedia moderator",
  "subtitle": "Asper tardus cariosus corrigo una crur consequatur atavus.",
  "paragraph1": "Pax tergeo cui acceptus tepidus. Rem tredecim cras defluo voveo blanditiis excepturi demens conturbo. Agnitio acerbitas tamisium umbra tui.\nClaustrum tremo thesaurus victus urbanus amplexus creator textus arca trado. Dedico decet cresco testimonium celo teneo accommodo cresco explicabo. Amo vicinus uberrime ater quo cado condico annus enim advenio.",
  "paragraph2": "Sollicito territo textor vestigium torqueo denuo. Coaegresco considero aurum pariatur. Dolor comitatus comedo decipio communis.\nDolores quibusdam tepesco tenus. Denuncio comptus tristis corrumpo depono depono. Pariatur abstergo provident tunc.",
  "image": "/images/img-4.jpg",
  "ctaText": "transition",
  "testimonial": "Carpo arma delego agnitio uxor ipsam fugit.",
  "name": "Dave Runolfsdottir"
}