{
  "slug": "template-504",
  "title": "Visionary asymmetric support",
  "subtitle": "Dolores accusator aiunt ipsam sortitus eius corpus vinum capillus tenax.",
  "paragraph1": "Attonbitus deorsum sollers vulgivagus ut virgo balbus porro. Deprimo dicta vespillo. Corrupti amor subseco virgo spectaculum decerno volutabrum cupressus.\nMaxime trado cimentarius vulariter subito impedit. Suspendo aut cum aestus. Administratio tollo altus articulus molestias tenuis conor similique.",
  "paragraph2": "Tenus tutamen cunctatio. Auctor tantum torqueo caritas infit. Agnitio versus dedico ultio alius appello coniuratio taceo comptus reprehenderit.\nBellicus peccatus candidus ultio comitatus aperio repudiandae temperantia summisse aranea. Vapulus taedium tricesimus accusator supellex velociter comprehendo nulla amplexus. Vinco culpo sophismata degero dicta curto adsum coniecto.",
  "image": "/images/img-5.jpg",
  "ctaText": "syndicate",
  "testimonial": "Acies stultus villa amet conservo.",
  "name": "Tiffany Bins V"
}