{
  "slug": "template-87",
  "title": "Synergistic cohesive capacity",
  "subtitle": "Defetiscor conqueror tredecim despecto adduco.",
  "paragraph1": "Solitudo caries amita reiciendis delinquo comburo vulgo coniecto theologus texo. Quos tabernus summa aiunt super adhuc aut utique. Tondeo tero synagoga curia crudelis praesentium defungo comparo vacuus deporto.\nAttollo necessitatibus delectus aurum ater vereor. Vox eos demulceo sono statua quis suscipit consequatur sui cedo. Caelum crur crur adicio suspendo aspernatur caelestis labore congregatio.",
  "paragraph2": "Debilito tabula tam est patria. Succedo vinculum atque soluta consequuntur vallum quo. Venia caterva ultio veritatis crastinus.\nSupra ter qui argentum claudeo umbra temeritas deputo aurum. Accusamus solitudo thorax thermae. Adhuc communis amo demo decumbo vomito quisquam tondeo molestiae vomica.",
  "image": "/images/img-3.jpg",
  "ctaText": "iterate",
  "testimonial": "Cenaculum tamisium solvo uberrime beatus.",
  "name": "Mrs. Molly Boyle"
}